{
  "providers": {
    "awscloudformation": {
      "AuthRoleName": "amplify-tipgov2-prodca-134718-authRole",
      "UnauthRoleArn": "arn:aws:iam::844178842851:role/amplify-tipgov2-prodca-134718-unauthRole",
      "AuthRoleArn": "arn:aws:iam::844178842851:role/amplify-tipgov2-prodca-134718-authRole",
      "Region": "ca-central-1",
      "DeploymentBucketName": "amplify-tipgov2-prodca-134718-deployment",
      "UnauthRoleName": "amplify-tipgov2-prodca-134718-unauthRole",
      "StackName": "amplify-tipgov2-prodca-134718",
      "StackId": "arn:aws:cloudformation:ca-central-1:844178842851:stack/amplify-tipgov2-prodca-134718/af46eda0-6810-11ed-b6f8-0ec1f0a54474",
      "AmplifyAppId": "d342z1f5gwadi0",
      "AuthTriggerTemplateURL": "https://s3.amazonaws.com/amplify-tipgov2-prodca-134718-deployment/amplify-cfn-templates/auth/auth-trigger-cloudformation-template.json"
    }
  },
  "function": {
    "tipgov2CustomMessage": {
      "build": true,
      "providerPlugin": "awscloudformation",
      "service": "Lambda",
      "output": {
        "Region": "ca-central-1",
        "Arn": "arn:aws:lambda:ca-central-1:844178842851:function:tipgov2CustomMessage-prodca",
        "Name": "tipgov2CustomMessage-prodca",
        "LambdaExecutionRole": "tipgov2CustomMessage-prodca"
      },
      "lastPushTimeStamp": "2023-09-18T21:41:34.180Z",
      "providerMetadata": {
        "s3TemplateURL": "https://s3.amazonaws.com/amplify-tipgov2-prodca-134718-deployment/amplify-cfn-templates/function/tipgov2CustomMessage-cloudformation-template.json",
        "logicalId": "functiontipgov2CustomMessage"
      },
      "s3Bucket": {
        "deploymentBucketName": "amplify-tipgov2-prodca-134718-deployment",
        "s3Key": "amplify-builds/tipgov2CustomMessage-62796561664338725364-build.zip"
      },
      "lastBuildTimeStamp": "2022-12-04T21:35:27.016Z",
      "lastBuildType": "PROD",
      "lastPackageTimeStamp": "2022-12-04T21:35:27.069Z",
      "distZipFilename": "tipgov2CustomMessage-62796561664338725364-build.zip",
      "lastPushDirHash": "5/CTgVuzteQM2JcVFnHcBp4+n54="
    }
  },
  "auth": {
    "tipgov2": {
      "service": "Cognito",
      "providerPlugin": "awscloudformation",
      "dependsOn": [
        {
          "category": "function",
          "resourceName": "tipgov2CustomMessage",
          "triggerProvider": "Cognito",
          "attributes": [
            "Arn",
            "Name"
          ]
        }
      ],
      "customAuth": false,
      "frontendAuthConfig": {
        "socialProviders": [],
        "usernameAttributes": [
          "EMAIL"
        ],
        "signupAttributes": [
          "EMAIL",
          "LOCALE"
        ],
        "passwordProtectionSettings": {
          "passwordPolicyMinLength": 8,
          "passwordPolicyCharacters": []
        },
        "mfaConfiguration": "OFF",
        "mfaTypes": [
          "SMS"
        ],
        "verificationMechanisms": [
          "EMAIL"
        ]
      },
      "output": {
        "UserPoolId": "ca-central-1_g83IQuJ6y",
        "AppClientIDWeb": "4kcvk3mm3vcuirmok9hfj1lsg6",
        "AppClientID": "52h02f23p1npcghp1aipkul3d7",
        "IdentityPoolId": "ca-central-1:b6b5eef4-9f00-4e37-84b2-86dd30f4c124",
        "UserPoolArn": "arn:aws:cognito-idp:ca-central-1:844178842851:userpool/ca-central-1_g83IQuJ6y",
        "IdentityPoolName": "tipgov2__prodca",
        "UserPoolName": "tipgov2"
      },
      "lastPushTimeStamp": "2023-09-18T21:41:34.182Z",
      "providerMetadata": {
        "s3TemplateURL": "https://s3.amazonaws.com/amplify-tipgov2-prodca-134718-deployment/amplify-cfn-templates/auth/tipgov2-cloudformation-template.json",
        "logicalId": "authtipgov2"
      }
    }
  },
  "api": {
    "tipgov2": {
      "service": "AppSync",
      "providerPlugin": "awscloudformation",
      "output": {
        "authConfig": {
          "defaultAuthentication": {
            "authenticationType": "AMAZON_COGNITO_USER_POOLS",
            "userPoolConfig": {
              "userPoolId": "authtipgov2"
            }
          },
          "additionalAuthenticationProviders": []
        },
        "GraphQLAPIIdOutput": "myvrcyku45gshjttp4r43mwb5q",
        "GraphQLAPIEndpointOutput": "https://7lzutil4hjholigee35upp4h7q.appsync-api.ca-central-1.amazonaws.com/graphql"
      },
      "lastPushTimeStamp": "2023-09-18T21:41:34.183Z",
      "providerMetadata": {
        "s3TemplateURL": "https://s3.amazonaws.com/amplify-tipgov2-prodca-134718-deployment/amplify-cfn-templates/api/cloudformation-template.json",
        "logicalId": "apitipgov2"
      },
      "lastPushDirHash": "djUeU1mWrtoQdalXqTEsyGEgjW0="
    }
  },
  "hosting": {
    "amplifyhosting": {
      "service": "amplifyhosting",
      "providerPlugin": "awscloudformation",
      "type": "manual",
      "providerMetadata": {
        "s3TemplateURL": "https://s3.amazonaws.com/amplify-tipgov2-prodca-134718-deployment/amplify-cfn-templates/hosting/amplifyhosting-template.json",
        "logicalId": "hostingamplifyhosting"
      },
      "lastPushTimeStamp": "2023-09-18T21:41:34.184Z",
      "output": {},
      "lastPushDirHash": "J7qHX4ZLNIdgHHxEYqQtgXXPASU="
    }
  },
  "storage": {
    "tipngov2profile": {
      "service": "S3",
      "providerPlugin": "awscloudformation",
      "dependsOn": [],
      "output": {
        "BucketName": "tipngov2profile134718-prodca",
        "Region": "ca-central-1"
      },
      "lastPushTimeStamp": "2023-09-18T21:41:36.025Z",
      "providerMetadata": {
        "s3TemplateURL": "https://s3.amazonaws.com/amplify-tipgov2-prodca-134718-deployment/amplify-cfn-templates/storage/cloudformation-template.json",
        "logicalId": "storagetipngov2profile"
      }
    }
  }
}